pyarmour/__init__.py
pyarmour/__main__.py
pyarmour/attacks.py
pyarmour/cli.py
pyarmour/decorators.py
pyarmour/utils.py
pyarmour/version.py
pyarmour/visualize.py
pyarmour/attacks/__init__.py
pyarmour/attacks/deepfool.py
pyarmour/attacks/fgsm.py
pyarmour/attacks/pgd.py
pyarmour/reports/__init__.py
pyarmour/reports/nlp.py
pyarmour/reports/vision.py
pyarmour-0.1.3.dist-info/LICENSE
pyarmour-0.1.3.dist-info/METADATA
pyarmour-0.1.3.dist-info/WHEEL
pyarmour-0.1.3.dist-info/entry_points.txt
pyarmour-0.1.3.dist-info/top_level.txt
pyarmour-0.1.3.dist-info/RECORD
