Metadata-Version: 2.1
Name: pyarmour
Version: 0.1.3
Summary: Zero-configuration adversarial robustness testing for ML models
Home-page: https://github.com/pyarmour/pyarmour
Author: PyArmour Team
Author-email: team@pyarmour.com
License: MIT
Project-URL: Bug Tracker, https://github.com/pyarmour/pyarmour/issues
Project-URL: Documentation, https://pyarmour.readthedocs.io
Project-URL: Source, https://github.com/pyarmour/pyarmour
Keywords: adversarial,machine learning,security,testing,numpy
Platform: any
Classifier: Programming Language :: Python :: 3
Classifier: Programming Language :: Python :: 3.8
Classifier: Programming Language :: Python :: 3.9
Classifier: Programming Language :: Python :: 3.10
Classifier: Programming Language :: Python :: 3.11
Classifier: License :: OSI Approved :: MIT License
Classifier: Operating System :: OS Independent
Classifier: Development Status :: 4 - Beta
Classifier: Intended Audience :: Developers
Classifier: Intended Audience :: Science/Research
Classifier: Topic :: Scientific/Engineering :: Artificial Intelligence
Classifier: Topic :: Security
Classifier: Topic :: Software Development :: Testing
Requires-Python: >=3.8
License-File: LICENSE
Requires-Dist: numpy>=1.24.0
Requires-Dist: matplotlib>=3.7.0
Requires-Dist: click>=8.1.0
Provides-Extra: dev
Requires-Dist: pytest>=7.4.0; extra == "dev"
Requires-Dist: black>=23.10.0; extra == "dev"
Requires-Dist: flake8>=6.1.0; extra == "dev"
Requires-Dist: mypy>=1.6.0; extra == "dev"
Requires-Dist: pre-commit>=3.3.3; extra == "dev"
Requires-Dist: sphinx>=7.1.2; extra == "dev"
Requires-Dist: sphinx-rtd-theme>=1.2.0; extra == "dev"
Requires-Dist: numpydoc>=1.5.0; extra == "dev"
